{
  "version": "0.1.3",
  "timestamp": "1670457600",
  "space": "sdbal.eth",
  "type": "proposal",
  "payload": {
    "name": "Gauge vote - BAL 15/12/2022 - 28/12/2022",
    "body": "Gauge vote for BAL inflation allocation.",
    "discussion": "https://app.balancer.fi/veBAL",
         "choices": [
            "20DAI-80TCR",
            "20USDC-40TEL-40DFX",
            "20WBTC-80BADGER",
            "20WETH-80CRE8R",
            "20WETH-80FDT",
            "20WETH-80HAUS",
            "20WETH-80T",
            "20WETH-80WNCG",
            "33auraBAL-33graviAURA-33WETH",
            "33DPX-33RDPX-33WETH",
            "33LUSD-33LQTY-33WETH",
            "40WBTC-40DIGG-20graviAURA",
            "50BADGER-50rETH",
            "50COMP-50WSTETH",
            "50COW-50GNO",
            "50COW-50WETH",
            "50DFX-50WETH",
            "50INV-50DOLA",
            "50MAGIC-50USDC",
            "50N/A-50N/A",
            "50OHM-25DAI-25WETH",
            "50OHM-50DAI",
            "50OHM-50WETH",
            "50RBW-50WETH",
            "50rETH-50bb-a-USD",
            "50rETH-50RPL",
            "50Silo-50WETH",
            "50STG-50bb-a-USD",
            "50TEMPLE-50bb-a-USD",
            "50VSTA-50WETH",
            "50WETH-50AURA",
            "50WETH-50FOLD",
            "50wstETH-50bb-a-USD",
            "50WSTETH-50LDO - 0xc2c2304E163e1aB…0B",
            "50wstETH-50LDO - 0x79C14b9655e1C4A…d3",
            "50WSTETH-50USDC",
            "80D2D-20USDC",
            "80palStkAAVE-20AAVE",
            "80SD-20maticX",
            "80TEMPLE-20DAI",
            "80TETU-20USDC",
            "B-33WETH-33WBTC-33USDC",
            "B-50COMP-50WETH",
            "B-50LINK-50WETH",
            "B-50MATIC-50WETH",
            "B-50REN-50WETH",
            "B-50SNX-50WETH",
            "B-50THX-50stMATIC",
            "B-50USDC-50WETH",
            "B-50VITA-50WETH",
            "B-50WBTC-50WETH - 0x4E3c048BE671852…ff",
            "B-50WBTC-50WETH - 0x211C27a32E68665…ab",
            "B-50WETH-50YFI",
            "B-60BAL-40WETH",
            "B-60WETH-40DAI",
            "B-80GNO-20WETH",
            "B-80LDO-20WETH",
            "B-80PICKLE-20WETH",
            "B-auraBAL-STABLE",
            "bb-am-usd",
            "bb-a-USD",
            "bb-HAPPY",
            "bb-rf-aUSD",
            "bb-rf-aUSD-asUSD",
            "bb-STG-USD",
            "bb-WONDER",
            "bb-wstETH",
            "bb-YELLOW",
            "B-MaticX-Stable",
            "BP-BTC-SP",
            "B-POLYBASE",
            "B-POLYDEFI - 0x5A3970E3145Bbba…9E",
            "B-POLYDEFI - 0xA80D514734e5769…F0",
            "BPSP",
            "BPTC",
            "BPT-LDO-WSTEH",
            "BPT-rETH-ETH",
            "B-rETH-STABLE",
            "B-sdBAL-STABLE",
            "B-stETH-STABLE - 0xcD4722B7c24C29e…aE",
            "B-stETH-Stable - 0x6f825C8bbf67eBb…8E",
            "B-stMATIC-Stable",
            "B-tetuQi-Stable",
            "cbETH-wstETH-BPT",
            "DOLA BSP",
            "FUD",
            "IBT-IBRETH",
            "Mai BSP",
            "MAI-BSP",
            "MAI-USDC-SP",
            "NWWP",
            "sfrxETH-stETH-rETH-BPT",
            "sNOTE-BPT",
            "staBAL3",
            "staBAL3-BTC",
            "TELX-50TEL-50BAL",
            "TELX-60TEL-20BAL-20USDC",
            "tetuBAL-BALWETH",
            "USDC-PAL",
            "VBPT",
            "veBAL",
            "VST BSP",
            "wstETH-ACX",
            "XSGD-USDC"
    ],
    "start": 1670457600,
    "end": 1670853600,
    "snapshot": 16136270,
    "type": "weighted",
    "metadata": { "plugins": {} }
  }
}
